sticker_decoders_python-0.1.0.dist-info/METADATA
sticker_decoders_python-0.1.0.dist-info/WHEEL
sticker.cpython-38-darwin.so
sticker_decoders_python-0.1.0.dist-info/RECORD
