Metadata-Version: 2.1
Name: sticker-decoders-python
Version: 0.1.0
Summary: Sticker Python module minus the models
Author: Tobias Pütz <puetztobias@gmail.com>, Daniël de Kok <me@danieldk.eu>
Author-Email: Tobias Pütz <puetztobias@gmail.com>, Daniël de Kok <me@danieldk.eu>
License: BlueOak-1.0.0
